ictruck/__init__.py
ictruck/configuration.py
ictruck/exceptions.py
ictruck/printers.py
ictruck/py.typed
ictruck/vehicles.py
ictruck/__/__init__.py
ictruck/__/imports.py
ictruck/__/miscellany.py
ictruck/__/nomina.py
ictruck/__/validators.py
ictruck/_typedecls/__builtins__.py
ictruck/_typedecls/icecream/__init__.pyi
ictruck/_typedecls/icecream/builtins.pyi
ictruck/_typedecls/icecream/icecream.pyi
ictruck/recipes/__.py
ictruck/recipes/__init__.py
ictruck/recipes/logging.py
ictruck/recipes/rich.py
ictruck/recipes/sundae.py
icecream_truck-1.5.dist-info/METADATA
icecream_truck-1.5.dist-info/WHEEL
icecream_truck-1.5.dist-info/licenses/LICENSE.txt
icecream_truck-1.5.dist-info/RECORD
