Metadata-Version: 2.4
Name: icecream-truck
Version: 1.5
Summary: Flexible factory for Icecream debuggers.
Project-URL: Homepage, https://github.com/emcd/python-icecream-truck
Project-URL: Documentation, https://emcd.github.io/python-icecream-truck
Project-URL: Download, https://pypi.org/project/icecream-truck/#files
Project-URL: Source Code, https://github.com/emcd/python-icecream-truck
Project-URL: Issue Tracker, https://github.com/emcd/python-icecream-truck/issues
Author-email: Eric McDonald <emcd@users.noreply.github.com>
License-Expression: Apache-2.0
License-File: LICENSE.txt
Keywords: debug,icecream,introspect
Classifier: Development Status :: 5 - Production/Stable
Classifier: Intended Audience :: Developers
Classifier: License :: OSI Approved :: Apache Software License
Classifier: Programming Language :: Python :: 3 :: Only
Classifier: Programming Language :: Python :: 3.10
Classifier: Programming Language :: Python :: 3.11
Classifier: Programming Language :: Python :: 3.12
Classifier: Programming Language :: Python :: 3.13
Classifier: Programming Language :: Python :: Implementation :: CPython
Classifier: Topic :: Software Development
Requires-Python: >=3.10
Requires-Dist: absence~=1.1
Requires-Dist: accretive~=4.1
Requires-Dist: colorama
Requires-Dist: frigid~=4.1
Requires-Dist: icecream
Requires-Dist: typing-extensions
Provides-Extra: rich
Requires-Dist: rich; extra == 'rich'
